constraintflow/__init__.py
constraintflow/cli.py
constraintflow/ast_cflow/__init__.py
constraintflow/ast_cflow/astBuilder.py
constraintflow/ast_cflow/astPrinter.py
constraintflow/ast_cflow/astTC.py
constraintflow/ast_cflow/astVisitor.py
constraintflow/ast_cflow/astcf.py
constraintflow/ast_cflow/dsl.g4
constraintflow/ast_cflow/dsl.interp
constraintflow/ast_cflow/dsl.tokens
constraintflow/ast_cflow/dslLexer.interp
constraintflow/ast_cflow/dslLexer.py
constraintflow/ast_cflow/dslLexer.tokens
constraintflow/ast_cflow/dslListener.py
constraintflow/ast_cflow/dslParser.py
constraintflow/ast_cflow/dslVisitor.py
constraintflow/compiler/__init__.py
constraintflow/compiler/codeGen.py
constraintflow/compiler/compile.py
constraintflow/compiler/convertToIr.py
constraintflow/compiler/globals.py
constraintflow/compiler/ir.py
constraintflow/compiler/irVisitor.py
constraintflow/compiler/representations.py
constraintflow/compiler/optimizations/__init__.py
constraintflow/compiler/optimizations/copyPropagation.py
constraintflow/compiler/optimizations/cse.py
constraintflow/compiler/optimizations/dce.py
constraintflow/compiler/optimizations/loopInvariantCodeMotion.py
constraintflow/compiler/optimizations/polyOpt.py
constraintflow/compiler/optimizations/print.py
constraintflow/compiler/optimizations/rewrite.py
constraintflow/compiler/optimizations/symexpCount.py
constraintflow/compiler/optimizations/uses.py
constraintflow/gbcsr/__init__.py
constraintflow/gbcsr/op_helper.py
constraintflow/gbcsr/plot.py
constraintflow/gbcsr/sparse_block.py
constraintflow/gbcsr/sparse_tensor.py
constraintflow/gbcsr/tensor_ops.py
constraintflow/lib/__init__.py
constraintflow/lib/abs_elem.py
constraintflow/lib/flow_sparse.py
constraintflow/lib/globals.py
constraintflow/lib/llist.py
constraintflow/lib/network.py
constraintflow/lib/parse.py
constraintflow/lib/polyexp.py
constraintflow/lib/spec.py
constraintflow/lib/symexp.py
constraintflow/verifier/__init__.py
constraintflow/verifier/provesound.py
constraintflow-0.1.1.dist-info/licenses/LICENSE
constraintflow-0.1.1.dist-info/METADATA
constraintflow-0.1.1.dist-info/WHEEL
constraintflow-0.1.1.dist-info/entry_points.txt
constraintflow-0.1.1.dist-info/top_level.txt
constraintflow-0.1.1.dist-info/RECORD
