Metadata-Version: 2.4
Name: constraintflow
Version: 0.1.1
Summary: A DSL and tools for neural network certification
Author: Avaljot Singh, Yasmin Sarita
License: MIT
Keywords: dsl,neural networks,certification,constraint solving
Classifier: Programming Language :: Python :: 3
Classifier: Operating System :: OS Independent
Requires-Python: >=3.9
License-File: LICENSE
Requires-Dist: graphviz==0.20.1
Requires-Dist: matplotlib==3.10.5
Requires-Dist: networkx==3.1
Requires-Dist: numpy==2.2.6
Requires-Dist: onnx==1.16.2
Requires-Dist: torch
Requires-Dist: torchvision
Requires-Dist: z3-solver==4.12.2.0
Requires-Dist: antlr4-python3-runtime==4.9.2
Requires-Dist: typer
Dynamic: license-file
